{
  "gitSyncId": "69e7d447c5e91666c08fb1a7_6e81d1ed-c8ef-4ccd-be7b-a603125dfcd1",
  "id": "Sales_GetSavedSalesInvoiceByNumber",
  "pluginId": "mysql-plugin",
  "pluginType": "DB",
  "unpublishedAction": {
    "actionConfiguration": {
      "body": "SELECT id\nFROM documents\nWHERE document_type = 'SALES_INVOICE'\n  AND document_number = {{ invoice_no.text }}\n  AND company_id = {{ appsmith.store.companyId }}\nORDER BY id DESC\nLIMIT 1;\n",
      "encodeParamsToggle": true,
      "paginationType": "NONE",
      "pluginSpecifiedTemplates": [
        {
          "value": true
        }
      ],
      "timeoutInMillisecond": 10000
    },
    "confirmBeforeExecute": false,
    "datasource": {
      "id": "Axon",
      "isAutoGenerated": false,
      "name": "Axon",
      "pluginId": "mysql-plugin"
    },
    "dynamicBindingPathList": [
      {
        "key": "body"
      }
    ],
    "name": "GetSavedSalesInvoiceByNumber",
    "pageId": "Sales",
    "runBehaviour": "MANUAL",
    "userSetOnLoad": false
  }
}