{
  "gitSyncId": "69e7d447c5e91666c08fb1a7_4b18bddb-7cc0-44c4-afb9-0f520b31a66f",
  "unpublishedPage": {
    "isHidden": false,
    "layouts": [
      {
        "dsl": {
          "backgroundColor": "none",
          "bottomRow": 380,
          "canExtend": true,
          "containerStyle": "none",
          "detachFromLayout": true,
          "dynamicBindingPathList": [],
          "leftColumn": 0,
          "minHeight": 550,
          "parentColumnSpace": 1,
          "parentRowSpace": 1,
          "rightColumn": 1224,
          "snapColumns": 64,
          "snapRows": 53,
          "topRow": 0,
          "type": "CANVAS_WIDGET",
          "version": 94,
          "widgetId": "0",
          "widgetName": "MainContainer"
        }
      }
    ],
    "name": "Reports",
    "slug": "reports"
  }
}