{
  "gitSyncId": "69e7d447c5e91666c08fb1a7_ade28bad-3f2b-4d14-82ea-12a600aa660f",
  "id": "POS_Getpartner",
  "pluginId": "mysql-plugin",
  "pluginType": "DB",
  "unpublishedAction": {
    "actionConfiguration": {
      "body": "SELECT\n    bp.id,\n    CONCAT(bp.code, ' - ', bp.name) AS label\nFROM business_partners bp\nWHERE bp.company_id = {{ appsmith.store.companyId}}\n  AND bp.is_active = 1\n  AND bp.partner_type IN ('CUSTOMER', 'BOTH')\nORDER BY bp.name;",
      "encodeParamsToggle": true,
      "paginationType": "NONE",
      "pluginSpecifiedTemplates": [
        {
          "value": true
        }
      ],
      "timeoutInMillisecond": 10000
    },
    "confirmBeforeExecute": false,
    "datasource": {
      "id": "Axon",
      "isAutoGenerated": false,
      "name": "Axon",
      "pluginId": "mysql-plugin"
    },
    "dynamicBindingPathList": [
      {
        "key": "body"
      }
    ],
    "name": "Getpartner",
    "pageId": "POS",
    "runBehaviour": "AUTOMATIC",
    "userSetOnLoad": false
  }
}